{
  "BARBED": {
    "name": "Barbed Wire",
    "amount": 2
  },
  "BEEPER": {
    "name": "Proximity Alarm",
    "amount": 2
  },
  "BLOCKER": {
    "name": "Observation Blocker",
    "amount": 3
  },
  "BREACH": {
    "name": "Breach Charge",
    "amount": 3
  },
  "C4": {
    "name": "Nitro Cell",
    "amount": 1
  },
  "CAMERA": {
    "name": "Bulletproof Camera",
    "amount": 1
  },
  "CLAYMORE": {
    "name": "Claymore",
    "amount": 2
  },
  "EMP": {
    "name": "Impact EMP Grenade",
    "amount": 2
  },
  "FRAG": {
    "name": "Frag Grenade",
    "amount": 2
  },
  "HARDBREACH": {
    "name": "Hard Breach Charge",
    "amount": 2
  },
  "IMPACT": {
    "name": "Impact Grenade",
    "amount": 2
  },
  "SHIELD": {
    "name": "Deployable Shield",
    "amount": 1
  },
  "SMOKE": {
    "name": "Smoke Grenade",
    "amount": 2
  },
  "STUN": {
    "name": "Stun Grenade",
    "amount": 2
  }
}